lcdscreen/__init__.py
lcdscreen/LCDScreen.py
lcdscreen-1.2.1.dist-info/DESCRIPTION.rst
lcdscreen-1.2.1.dist-info/METADATA
lcdscreen-1.2.1.dist-info/metadata.json
lcdscreen-1.2.1.dist-info/RECORD
lcdscreen-1.2.1.dist-info/WHEEL
lcdscreen-1.2.1.dist-info/top_level.txt
