Metadata-Version: 2.0
Name: lcdscreen
Version: 1.2.1
Summary: A class to write to a LCD Screen using a raspberry pi
Home-page: https://github.com/mikestreety/pypi-lcdscreen
Author: Mike Street
Author-email: mikestreety@gmail.com
License: MIT
Keywords: raspberry pi lcd screen
Platform: UNKNOWN
Classifier: Programming Language :: Python :: 2.7
Classifier: Development Status :: 4 - Beta
Classifier: Topic :: System :: Hardware
Classifier: License :: OSI Approved :: BSD License
Classifier: Programming Language :: Python
